ctoybox-0.4.2.dist-info/METADATA
ctoybox-0.4.2.dist-info/WHEEL
ctoybox/__init__.py
ctoybox/json_schema.py
ctoybox/input.py
ctoybox/human_play.py
ctoybox/ffi.py
ctoybox/ctoybox/__init__.py
ctoybox/ctoybox/ffi.py
ctoybox/ctoybox/native.so
ctoybox-0.4.2.dist-info/RECORD
